plover_retro_untranslator/__init__.py
plover_retro_untranslator/additional_american_spellings.json
plover_retro_untranslator/american_spellings.json
plover_retro_untranslator/spelling_converter.py
plover_retro_untranslator-0.4.4.dist-info/LICENSE
plover_retro_untranslator-0.4.4.dist-info/METADATA
plover_retro_untranslator-0.4.4.dist-info/WHEEL
plover_retro_untranslator-0.4.4.dist-info/entry_points.txt
plover_retro_untranslator-0.4.4.dist-info/top_level.txt
plover_retro_untranslator-0.4.4.dist-info/zip-safe
plover_retro_untranslator-0.4.4.dist-info/RECORD
