Metadata-Version: 2.1
Name: plover_retro_untranslator
Version: 0.4.4
Summary: Converts the last X translations to a specified format consisting of raw steno and/or a translation
Home-page: https://github.com/Josiah-tan/plover-retro-untranslator
Author: Josiah-tan
License: GNU General Public License v3 (GPLv3)
Keywords: plover plover_plugin plover_retro_untranslator
Classifier: Development Status :: 4 - Beta
Classifier: Environment :: Plugins
Classifier: Intended Audience :: End Users/Desktop
Classifier: License :: OSI Approved :: GNU General Public License v3 (GPLv3)
Classifier: Operating System :: OS Independent
Classifier: Programming Language :: Python :: 3
Classifier: Programming Language :: Python :: 3.6
Classifier: Programming Language :: Python :: 3.7
Classifier: Programming Language :: Python :: 3.8
Classifier: Programming Language :: Python :: 3.9
Classifier: Programming Language :: Python :: 3.10
License-File: LICENSE
Requires-Dist: plover >=4.0.0.dev8
Requires-Dist: PyQt5 >=5.5
